aPrioriDNS/DNS.py
aPrioriDNS/NN.py
aPrioriDNS/__init__.py
aPrioriDNS/_data_struct.py
aPrioriDNS/_styles.py
aPrioriDNS/_utils.py
aPrioriDNS/_variables.py
aPrioriDNS/plot_utilities.py
aprioridns-1.1.10.dist-info/METADATA
aprioridns-1.1.10.dist-info/WHEEL
aprioridns-1.1.10.dist-info/licenses/LICENSE
aprioridns-1.1.10.dist-info/RECORD
