Metadata-Version: 2.4
Name: aPrioriDNS
Version: 1.1.10
Summary: A python package to process Direct Numerical Simulations
Project-URL: Homepage, https://github.com/LorenzoPiu/aPrioriDNS
Project-URL: Issues, https://github.com/LorenzoPiu/aPrioriDNS/issues
Project-URL: Documentation, https://apriori.gitbook.io
Author-email: Lorenzo Piu <lorenzo.piu@ulb.be>
License-File: LICENSE
Classifier: License :: OSI Approved :: MIT License
Classifier: Operating System :: OS Independent
Classifier: Programming Language :: Python :: 3
Requires-Python: >=3.8
Requires-Dist: cantera>=3.0.0
Requires-Dist: matplotlib>=3.2.0
Requires-Dist: numpy>=1.18.0
Requires-Dist: requests>=2.32.0
Requires-Dist: scipy>=1.12.0
Requires-Dist: tabulate>=0.9.0
